LICENSE
great_asset/__init__.py
great_asset/crypt.py
great_asset/enums.py
great_asset/item.py
great_asset/py.typed
great_asset/save_file.py
great_asset/types_/__init__.py
great_asset/types_/challenge_file.py
great_asset/types_/config_file.py
great_asset/types_/save_file.py
great_asset/types_/shared.py
great_asset/utils.py
great_asset/vector.py
great_asset-1.2.0.dist-info/LICENSE
great_asset-1.2.0.dist-info/METADATA
great_asset-1.2.0.dist-info/WHEEL
great_asset-1.2.0.dist-info/RECORD
