Metadata-Version: 2.1
Name: great_asset
Version: 1.2.0
Summary: A small headless library for editing Lethal Company save files.
Home-page: https://github.com/AbstractUmbra/great_asset
License: MIT
Keywords: save-editor,wrapper,lethal-company
Author: Alex Nørgaard
Author-email: umbra@abstractumbra.dev
Requires-Python: >=3.8,<4.0
Classifier: Intended Audience :: Education
Classifier: Intended Audience :: End Users/Desktop
Classifier: License :: OSI Approved :: MIT License
Classifier: Natural Language :: English
Classifier: Operating System :: OS Independent
Classifier: Programming Language :: Python :: 3
Classifier: Programming Language :: Python :: 3.8
Classifier: Programming Language :: Python :: 3.9
Classifier: Programming Language :: Python :: 3.10
Classifier: Programming Language :: Python :: 3.11
Classifier: Programming Language :: Python :: 3.12
Classifier: Topic :: Internet
Classifier: Typing :: Typed
Provides-Extra: speed
Requires-Dist: orjson ; extra == "speed"
Requires-Dist: pycryptodome (>=3.19.0,<4.0.0)
Project-URL: Discord, https://discord.gg/aYGYJxwqe5
Project-URL: Issue Tracker, https://github.com/AbstractUmbra/GreatAsset/issues
Project-URL: Repository, https://github.com/AbstractUmbra/great_asset
